gitlab_kaban_report/__init__.py
gitlab_kaban_report/api_interface.py
gitlab_kaban_report/constants.py
gitlab_kaban_report/encrypt.py
gitlab_kaban_report/logo.py
gitlab_kaban_report/main_interface.py
gitlab_kanban_report-1.1.data/scripts/gitlab_report
gitlab_kanban_report-1.1.dist-info/LICENSE.txt
gitlab_kanban_report-1.1.dist-info/METADATA
gitlab_kanban_report-1.1.dist-info/WHEEL
gitlab_kanban_report-1.1.dist-info/top_level.txt
gitlab_kanban_report-1.1.dist-info/RECORD
